passuth/__init__.py
passuth/passuth.pyi
passuth/py.typed
passuth/__main__.py
passuth/passuth.graalpy242-311-native-x86_64-darwin.so
passuth-0.3.2.dist-info/RECORD
passuth-0.3.2.dist-info/WHEEL
passuth-0.3.2.dist-info/entry_points.txt
passuth-0.3.2.dist-info/METADATA
passuth-0.3.2.dist-info/licenses/LICENSE
